pycallnumber/__init__.py
pycallnumber/exceptions.py
pycallnumber/factories.py
pycallnumber/options.py
pycallnumber/set.py
pycallnumber/settings.py
pycallnumber/template.py
pycallnumber/unit.py
pycallnumber/utils.py
pycallnumber/units/__init__.py
pycallnumber/units/compound.py
pycallnumber/units/numbers.py
pycallnumber/units/simple.py
pycallnumber/units/callnumbers/__init__.py
pycallnumber/units/callnumbers/dewey.py
pycallnumber/units/callnumbers/lc.py
pycallnumber/units/callnumbers/local.py
pycallnumber/units/callnumbers/parts.py
pycallnumber/units/callnumbers/sudoc.py
pycallnumber/units/dates/__init__.py
pycallnumber/units/dates/base.py
pycallnumber/units/dates/datestring.py
pycallnumber/units/dates/parts.py
pycallnumber-0.2.0.dist-info/LICENSE
pycallnumber-0.2.0.dist-info/METADATA
pycallnumber-0.2.0.dist-info/WHEEL
pycallnumber-0.2.0.dist-info/top_level.txt
pycallnumber-0.2.0.dist-info/RECORD
