Metadata-Version: 2.1
Name: pycallnumber
Version: 0.2.0
Summary: A Python library for parsing call numbers.
Author: Jason Thomale
Author-email: jason.thomale@unt.edu
Maintainer: University of North Texas Libraries
License: BSD
Project-URL: homepage, https://github.com/unt-libraries/pycallnumber
Keywords: python,callnumber,callnumbers,call number,call numbers
Classifier: Development Status :: 5 - Production/Stable
Classifier: Intended Audience :: Education
Classifier: Intended Audience :: Developers
Classifier: Natural Language :: English
Classifier: License :: OSI Approved :: BSD License
Classifier: Programming Language :: Python
Classifier: Programming Language :: Python :: 2
Classifier: Programming Language :: Python :: 2.7
Classifier: Programming Language :: Python :: 3
Classifier: Programming Language :: Python :: 3.5
Classifier: Programming Language :: Python :: 3.6
Classifier: Programming Language :: Python :: 3.7
Classifier: Programming Language :: Python :: 3.8
Classifier: Programming Language :: Python :: 3.9
Classifier: Programming Language :: Python :: 3.10
Classifier: Programming Language :: Python :: 3.11
Classifier: Topic :: Software Development
License-File: LICENSE
Requires-Dist: importlib-metadata (>=2.0.0) ; python_version <= "3.7"
Requires-Dist: future ; python_version == "2.7"
Provides-Extra: dev
Requires-Dist: pytest (>=3.5.0) ; (python_version < "3.10") and extra == 'dev'
Requires-Dist: pytest (>=6.2.4) ; (python_version >= "3.10") and extra == 'dev'
